funcodec/__init__.py
funcodec/version.txt
funcodec/bin/__init__.py
funcodec/bin/codec_inference.py
funcodec/bin/codec_train.py
funcodec/bin/text2audio_inference.py
funcodec/bin/text2audio_train.py
funcodec/datasets/__init__.py
funcodec/datasets/collate_fn.py
funcodec/datasets/dataset.py
funcodec/datasets/iterable_dataset.py
funcodec/datasets/preprocessor.py
funcodec/datasets/large_datasets/__init__.py
funcodec/datasets/large_datasets/build_dataloader.py
funcodec/datasets/large_datasets/dataset.py
funcodec/datasets/large_datasets/datapipes/__init__.py
funcodec/datasets/large_datasets/datapipes/batch.py
funcodec/datasets/large_datasets/datapipes/filter.py
funcodec/datasets/large_datasets/datapipes/map.py
funcodec/datasets/large_datasets/utils/__init__.py
funcodec/datasets/large_datasets/utils/clipping.py
funcodec/datasets/large_datasets/utils/filter.py
funcodec/datasets/large_datasets/utils/low_frame_rate.py
funcodec/datasets/large_datasets/utils/padding.py
funcodec/datasets/large_datasets/utils/tokenize.py
funcodec/fileio/__init__.py
funcodec/fileio/codec_loader.py
funcodec/fileio/datadir_writer.py
funcodec/fileio/npy_scp.py
funcodec/fileio/rand_gen_dataset.py
funcodec/fileio/read_text.py
funcodec/fileio/sound_scp.py
funcodec/iterators/__init__.py
funcodec/iterators/abs_iter_factory.py
funcodec/iterators/chunk_iter_factory.py
funcodec/iterators/multiple_iter_factory.py
funcodec/iterators/sequence_iter_factory.py
funcodec/layers/__init__.py
funcodec/layers/abs_normalize.py
funcodec/layers/complex_utils.py
funcodec/layers/global_mvn.py
funcodec/layers/inversible_interface.py
funcodec/layers/label_aggregation.py
funcodec/layers/log_mel.py
funcodec/layers/mask_along_axis.py
funcodec/layers/sinc_conv.py
funcodec/layers/stft.py
funcodec/layers/time_warp.py
funcodec/layers/utterance_mvn.py
funcodec/lm/__init__.py
funcodec/lm/abs_model.py
funcodec/lm/espnet_model.py
funcodec/lm/seq_rnn_lm.py
funcodec/lm/transformer_lm.py
funcodec/losses/__init__.py
ms_funcodec-0.2.0.dist-info/LICENSE
ms_funcodec-0.2.0.dist-info/METADATA
ms_funcodec-0.2.0.dist-info/WHEEL
ms_funcodec-0.2.0.dist-info/top_level.txt
ms_funcodec-0.2.0.dist-info/RECORD
